{
  "loli": "./images/loli.jpg",
  "shaofu": "./images/shaofu.jpg",
  "shunv": "./images/shunv.jpg",
  "renqi": "./images/renqi.jpg",
  "yujie": "./images/yujie.jpg",
  "nvwang": "./images/nvwang.jpg",
  "daxiaojie": "./images/daxiaojie.jpg",
  "qianjin": "./images/qianjin.jpg",
  "fengpi": "./images/fengpi.jpg",
  "bingjiao": "./images/bingjiao.jpg",
  "shaonv": "./images/shaonv.jpg",
  "tianmei": "./images/tianmei.jpg",
  "ruanmei": "./images/ruanmei.jpg",
  "yuanqiniang": "./images/yuanqiniang.jpg",
  "aojiao": "./images/aojiao.jpg",
  "tiandandai": "./images/tiandandai.jpg",
  "sanwu": "./images/sanwu.jpg",
  "bingshan": "./images/bingshan.jpg",
  "kujie": "./images/kujie.jpg",
  "meihuo": "./images/meihuo.jpg",
  "meimo": "./images/meimo.jpg",
  "lamei": "./images/lamei.jpg",
  "jinyu": "./images/jinyu.jpg",
  "jixieji": "./images/jixieji.jpg",
  "weiniang": "./images/weiniang.jpg",
  "nanzhuangdalao": "./images/nanzhuangdalao.jpg",
  "senxi": "./images/senxi.jpg",
  "gufeng": "./images/gufeng.jpg",
  "wenyixi": "./images/wenyixi.jpg",
  "dushe": "./images/dushe.jpg",
  "xuejie": "./images/xuejie.jpg",
  "yundongxi": "./images/yundongxi.jpg",
  "linjianvh": "./images/linjianvh.jpg",
  "xuemei": "./images/xuemei.jpg",
  "chunyu": "./images/chunyu.jpg",
  "shouerniang": "./images/shouerniang.jpg",
  "monv": "./images/monv.jpg",
  "xianv": "./images/xianv.jpg",
  "OL": "./images/OL.jpg",
  "fuhei": "./images/fuhei.jpg"
}